{
    "name": "Stress",
    "docs": "https://github.com/BME-nodeservers/udi-stress-poly/README.md",
    "type": "python3",
    "executable": "negative.py",
    "install": "install.sh",
    "description": "Stress test ISY/Polyglot by creating a lot of nodes with a lot of driversSY",
    "notice": "",
    "shortPoll": "60",
    "longPoll": "600",
	"logLevel": "WARNING",
    "profile_version": "1.0.0",
	"customParams": {
		"Nodes" : "",
		"Cycles" : 0,
		"getDrivers": "FALSE",
		"multiplier": 1
	},
    "credits": [
    	{
    		"title": "Stress: Stress testing ISY/Polyglot",
    		"author": "Bob Paauwe",
    		"version": "1.1.0",
    		"date": "August 9, 2021",
    		"source": "https://github.com/BME-nodeservers/udi-stress-poly",
			"license": "https://github.com/BME-nodeservers/udi-sress-poly/LICENSE"
		}
	],
	"store" : {
		"developer": "bpaauwe@bobsplace.com",
		"price": 0.00,
		"recurring": 0,
		"recurring_interval": "month",
		"recurring_period": 0
	}
}
